LICENSE
MANIFEST.in
README.md
requirements.txt
setup.cfg
setup.py
src/pyVirtualize/__init__.py
src/pyVirtualize.egg-info/PKG-INFO
src/pyVirtualize.egg-info/SOURCES.txt
src/pyVirtualize.egg-info/dependency_links.txt
src/pyVirtualize.egg-info/not-zip-safe
src/pyVirtualize.egg-info/requires.txt
src/pyVirtualize.egg-info/top_level.txt
src/pyVirtualize/pyvSphere/__init__.py
src/pyVirtualize/pyvSphere/_base.py
src/pyVirtualize/pyvSphere/datacenter.py
src/pyVirtualize/pyvSphere/host.py
src/pyVirtualize/pyvSphere/datastore/__init__.py
src/pyVirtualize/pyvSphere/datastore/_base.py
src/pyVirtualize/pyvSphere/vm/__init__.py
src/pyVirtualize/pyvSphere/vm/_base.py
src/pyVirtualize/pyvSphere/vm/operation/__init__.py
src/pyVirtualize/pyvSphere/vm/operation/_base.py
src/pyVirtualize/pyvSphere/vm/operation/admin.py
src/pyVirtualize/pyvSphere/vm/operation/file.py
src/pyVirtualize/pyvSphere/vm/operation/power.py
src/pyVirtualize/pyvSphere/vm/operation/process.py
src/pyVirtualize/pyvSphere/vm/operation/snapshot.py
src/pyVirtualize/pyvSphere/vm/operation/vmutils.py
src/pyVirtualize/utils/__init__.py
src/pyVirtualize/utils/exceptions.py
src/pyVirtualize/utils/jsonutils.py
src/pyVirtualize/utils/klasses.py
src/pyVirtualize/utils/parsers.py
src/pyVirtualize/utils/winutils.py